[{"id":11339,"date":1688244000000,"product_code":"NH575","sales_period":false,"deal":false,"deal_code":"NA","customer_code":"LD724","online":true},{"id":11340,"date":1618650023000,"product_code":"NH575","sales_period":false,"deal":true,"deal_code":"SB477","customer_code":"JW881","online":true},{"id":11341,"date":1641324407000,"product_code":"DP527","sales_period":true,"deal":false,"deal_code":"NA","customer_code":"PL579","online":true},{"id":11342,"date":1637176263000,"product_code":"DK984","sales_period":false,"deal":true,"deal_code":"AP109","customer_code":"PH201","online":true},{"id":11343,"date":1673135920000,"product_code":"DD980","sales_period":false,"deal":true,"deal_code":"LS105","customer_code":"TC312","online":true},{"id":11344,"date":1674447171000,"product_code":"DM420","sales_period":true,"deal":false,"deal_code":"NA","customer_code":"DF968","online":true},{"id":11345,"date":1685989473000,"product_code":"PS755","sales_period":true,"deal":true,"deal_code":"AP109","customer_code":"EH359","online":false},{"id":11346,"date":1659549594000,"product_code":"DD980","sales_period":true,"deal":false,"deal_code":"NA","customer_code":"CG504","online":true},{"id":11347,"date":1670328949000,"product_code":"MD365","sales_period":false,"deal":true,"deal_code":"DM225","customer_code":"JP848","online":true},{"id":11348,"date":1646025804000,"product_code":"SL845","sales_period":false,"deal":true,"deal_code":"BL401","customer_code":"EC526","online":true},{"id":11349,"date":1657848477000,"product_code":"AL495","sales_period":false,"deal":false,"deal_code":"NA","customer_code":"CS612","online":true},{"id":11350,"date":1673503308000,"product_code":"ML688","sales_period":true,"deal":false,"deal_code":"NA","customer_code":"LB814","online":true},{"id":11351,"date":1668828019000,"product_code":"DM420","sales_period":false,"deal":true,"deal_code":"LS105","customer_code":"MM768","online":true},{"id":11352,"date":1659748517000,"product_code":"DM420","sales_period":true,"deal":false,"deal_code":"NA","customer_code":"SH279","online":true},{"id":11353,"date":1624510023000,"product_code":"SL845","sales_period":false,"deal":true,"deal_code":"AP109","customer_code":"AK303","online":true},{"id":11354,"date":1658311691000,"product_code":"WM660","sales_period":false,"deal":false,"deal_code":"NA","customer_code":"PJ945","online":true},{"id":11355,"date":1629950889000,"product_code":"DP527","sales_period":false,"deal":false,"deal_code":"NA","customer_code":"CB591","online":true},{"id":11356,"date":1674882769000,"product_code":"DM420","sales_period":false,"deal":true,"deal_code":"AP109","customer_code":"CB919","online":true},{"id":11357,"date":1610335419000,"product_code":"SL845","sales_period":true,"deal":true,"deal_code":"BL401","customer_code":"CJ691","online":true},{"id":11358,"date":1609763656000,"product_code":"DG813","sales_period":true,"deal":false,"deal_code":"NA","customer_code":"EG345","online":true},{"id":11359,"date":1656718902000,"product_code":"GD124","sales_period":false,"deal":false,"deal_code":"NA","customer_code":"CJ890","online":true},{"id":11360,"date":1660191561000,"product_code":"DK984","sales_period":true,"deal":false,"deal_code":"NA","customer_code":"MJ662","online":true},{"id":11361,"date":1674860550000,"product_code":"SL845","sales_period":true,"deal":false,"deal_code":"NA","customer_code":"JJ242","online":true},{"id":11362,"date":1636803171000,"product_code":"RM246","sales_period":false,"deal":false,"deal_code":"NA","customer_code":"EB286","online":true},{"id":11363,"date":1628620314000,"product_code":"BD603","sales_period":false,"deal":true,"deal_code":"DM225","customer_code":"BE275","online":true},{"id":11364,"date":1622879089000,"product_code":"BD603","sales_period":true,"deal":false,"deal_code":"NA","customer_code":"AW510","online":true},{"id":11365,"date":1691042362000,"product_code":"HI384","sales_period":false,"deal":false,"deal_code":"NA","customer_code":"AS499","online":true},{"id":11366,"date":1659744307000,"product_code":"NH575","sales_period":true,"deal":false,"deal_code":"NA","customer_code":"NT986","online":true},{"id":11367,"date":1643232749000,"product_code":"SL845","sales_period":true,"deal":false,"deal_code":"NA","customer_code":"JC337","online":true},{"id":11368,"date":1610606891000,"product_code":"DP527","sales_period":true,"deal":true,"deal_code":"DM225","customer_code":"EJ443","online":true},{"id":11369,"date":1615299693000,"product_code":"DP527","sales_period":false,"deal":false,"deal_code":"NA","customer_code":"AD780","online":true},{"id":11370,"date":1620928412000,"product_code":"DM420","sales_period":false,"deal":false,"deal_code":"NA","customer_code":"TC559","online":true},{"id":11371,"date":1611587268000,"product_code":"NH575","sales_period":true,"deal":true,"deal_code":"DM225","customer_code":"CB823","online":true},{"id":11372,"date":1622015440000,"product_code":"HI384","sales_period":false,"deal":false,"deal_code":"NA","customer_code":"DH491","online":true},{"id":11373,"date":1660574503000,"product_code":"AL495","sales_period":true,"deal":true,"deal_code":"SB477","customer_code":"CH163","online":false},{"id":11374,"date":1610620279000,"product_code":"DD980","sales_period":false,"deal":true,"deal_code":"LS105","customer_code":"IB646","online":true},{"id":11375,"date":1614502256000,"product_code":"DD980","sales_period":false,"deal":false,"deal_code":"NA","customer_code":"SM100","online":true},{"id":11376,"date":1631645151000,"product_code":"PD765","sales_period":false,"deal":false,"deal_code":"NA","customer_code":"CS616","online":true},{"id":11377,"date":1686094601000,"product_code":"DL822","sales_period":false,"deal":true,"deal_code":"BL401","customer_code":"SR298","online":true},{"id":11378,"date":1652717279000,"product_code":"AL495","sales_period":false,"deal":false,"deal_code":"NA","customer_code":"VO214","online":true},{"id":11379,"date":1646620897000,"product_code":"ML688","sales_period":false,"deal":true,"deal_code":"AP109","customer_code":"EL320","online":true},{"id":11380,"date":1639576970000,"product_code":"HI384","sales_period":false,"deal":false,"deal_code":"NA","customer_code":"MR223","online":true},{"id":11381,"date":1660473614000,"product_code":"AL495","sales_period":true,"deal":false,"deal_code":"NA","customer_code":"JW680","online":true},{"id":11382,"date":1673175345000,"product_code":"NH575","sales_period":true,"deal":false,"deal_code":"NA","customer_code":"MS340","online":true},{"id":11383,"date":1648245979000,"product_code":"DD980","sales_period":false,"deal":true,"deal_code":"SB477","customer_code":"TR130","online":true},{"id":11384,"date":1618463193000,"product_code":"PS755","sales_period":false,"deal":false,"deal_code":"NA","customer_code":"TJ753","online":true},{"id":11385,"date":1669293634000,"product_code":"AL495","sales_period":false,"deal":true,"deal_code":"SB477","customer_code":"SW260","online":true},{"id":11386,"date":1667895406000,"product_code":"DL822","sales_period":false,"deal":false,"deal_code":"NA","customer_code":"SB554","online":true},{"id":11387,"date":1687109254000,"product_code":"PS755","sales_period":false,"deal":true,"deal_code":"SB477","customer_code":"MA785","online":true},{"id":11388,"date":1664804231000,"product_code":"NH575","sales_period":false,"deal":true,"deal_code":"BL401","customer_code":"MR968","online":true},{"id":11389,"date":1643514160000,"product_code":"DP527","sales_period":true,"deal":false,"deal_code":"NA","customer_code":"ER565","online":true},{"id":11390,"date":1617113889000,"product_code":"NH575","sales_period":false,"deal":true,"deal_code":"DM225","customer_code":"MK352","online":false},{"id":11391,"date":1630162607000,"product_code":"DL822","sales_period":false,"deal":false,"deal_code":"NA","customer_code":"MS152","online":true},{"id":11392,"date":1686198428000,"product_code":"SL845","sales_period":true,"deal":true,"deal_code":"SB477","customer_code":"AS702","online":true},{"id":11393,"date":1621614694000,"product_code":"DP527","sales_period":false,"deal":false,"deal_code":"NA","customer_code":"ET214","online":true},{"id":11394,"date":1693252334000,"product_code":"AL495","sales_period":false,"deal":false,"deal_code":"NA","customer_code":"CF394","online":true},{"id":11395,"date":1634376145000,"product_code":"AL495","sales_period":false,"deal":true,"deal_code":"DM225","customer_code":"TF462","online":true},{"id":11396,"date":1618521019000,"product_code":"DL822","sales_period":false,"deal":false,"deal_code":"NA","customer_code":"CP708","online":true},{"id":11397,"date":1661300732000,"product_code":"HI384","sales_period":true,"deal":false,"deal_code":"NA","customer_code":"CJ524","online":true},{"id":11398,"date":1683666420000,"product_code":"ML688","sales_period":false,"deal":false,"deal_code":"NA","customer_code":"RH777","online":true},{"id":11399,"date":1638353580000,"product_code":"DP527","sales_period":false,"deal":false,"deal_code":"NA","customer_code":"JH570","online":true},{"id":11400,"date":1686362577000,"product_code":"AL495","sales_period":false,"deal":false,"deal_code":"NA","customer_code":"JW872","online":true},{"id":11401,"date":1641370478000,"product_code":"DD980","sales_period":true,"deal":false,"deal_code":"NA","customer_code":"AB535","online":true},{"id":11402,"date":1626178671000,"product_code":"GD124","sales_period":true,"deal":false,"deal_code":"NA","customer_code":"AW449","online":true},{"id":11403,"date":1688355261000,"product_code":"RM246","sales_period":false,"deal":true,"deal_code":"BL401","customer_code":"LS599","online":true},{"id":11404,"date":1672878114000,"product_code":"RM246","sales_period":true,"deal":true,"deal_code":"AP109","customer_code":"JW103","online":true},{"id":11405,"date":1610565476000,"product_code":"MD365","sales_period":true,"deal":false,"deal_code":"NA","customer_code":"JJ974","online":true},{"id":11406,"date":1611767748000,"product_code":"GD124","sales_period":false,"deal":false,"deal_code":"NA","customer_code":"RE668","online":true},{"id":11407,"date":1628116634000,"product_code":"DK984","sales_period":false,"deal":true,"deal_code":"SB477","customer_code":"LK293","online":true},{"id":11408,"date":1629721518000,"product_code":"PD765","sales_period":false,"deal":false,"deal_code":"NA","customer_code":"DB187","online":false},{"id":11409,"date":1674317267000,"product_code":"BD603","sales_period":true,"deal":false,"deal_code":"NA","customer_code":"RP896","online":true},{"id":11410,"date":1689671663000,"product_code":"DK984","sales_period":false,"deal":false,"deal_code":"NA","customer_code":"TM823","online":false},{"id":11411,"date":1672525456000,"product_code":"SL845","sales_period":false,"deal":false,"deal_code":"NA","customer_code":"BO517","online":true},{"id":11412,"date":1616183228000,"product_code":"DM420","sales_period":false,"deal":false,"deal_code":"NA","customer_code":"RS804","online":true},{"id":11413,"date":1622682451000,"product_code":"HI384","sales_period":true,"deal":false,"deal_code":"NA","customer_code":"MF592","online":true},{"id":11414,"date":1614462253000,"product_code":"PS755","sales_period":false,"deal":false,"deal_code":"NA","customer_code":"SC242","online":true},{"id":11415,"date":1620938875000,"product_code":"RS630","sales_period":false,"deal":true,"deal_code":"DM225","customer_code":"GJ689","online":true},{"id":11416,"date":1613347753000,"product_code":"WM660","sales_period":false,"deal":false,"deal_code":"NA","customer_code":"HH673","online":true},{"id":11417,"date":1637155675000,"product_code":"RS630","sales_period":false,"deal":false,"deal_code":"NA","customer_code":"ME796","online":true},{"id":11418,"date":1676847442000,"product_code":"PD765","sales_period":false,"deal":false,"deal_code":"NA","customer_code":"CB110","online":true},{"id":11419,"date":1676968586000,"product_code":"DG813","sales_period":false,"deal":false,"deal_code":"NA","customer_code":"RC459","online":true},{"id":11420,"date":1658900935000,"product_code":"WM660","sales_period":false,"deal":true,"deal_code":"AP109","customer_code":"JC105","online":true},{"id":11421,"date":1656401570000,"product_code":"DD980","sales_period":false,"deal":false,"deal_code":"NA","customer_code":"MB190","online":true},{"id":11422,"date":1691724409000,"product_code":"MD365","sales_period":false,"deal":false,"deal_code":"NA","customer_code":"HN546","online":true},{"id":11423,"date":1686968792000,"product_code":"RM246","sales_period":true,"deal":false,"deal_code":"NA","customer_code":"LC857","online":true},{"id":11424,"date":1611095687000,"product_code":"DG813","sales_period":true,"deal":false,"deal_code":"NA","customer_code":"SE335","online":true},{"id":11425,"date":1692682047000,"product_code":"DD980","sales_period":false,"deal":false,"deal_code":"NA","customer_code":"AK722","online":true},{"id":11426,"date":1642927833000,"product_code":"MD365","sales_period":false,"deal":false,"deal_code":"NA","customer_code":"KP445","online":true},{"id":11427,"date":1688217388000,"product_code":"PD765","sales_period":false,"deal":false,"deal_code":"NA","customer_code":"HH500","online":true},{"id":11428,"date":1629371373000,"product_code":"NH575","sales_period":false,"deal":false,"deal_code":"NA","customer_code":"JB682","online":true},{"id":11429,"date":1632775736000,"product_code":"BD603","sales_period":false,"deal":true,"deal_code":"DM225","customer_code":"JH710","online":true},{"id":11430,"date":1610459252000,"product_code":"DP527","sales_period":true,"deal":false,"deal_code":"NA","customer_code":"MJ926","online":true},{"id":11431,"date":1662987658000,"product_code":"DD980","sales_period":false,"deal":false,"deal_code":"NA","customer_code":"LJ583","online":true},{"id":11432,"date":1621962085000,"product_code":"DP527","sales_period":false,"deal":false,"deal_code":"NA","customer_code":"JJ909","online":false},{"id":11433,"date":1666197807000,"product_code":"DK984","sales_period":false,"deal":true,"deal_code":"AP109","customer_code":"BW540","online":true},{"id":11434,"date":1653266839000,"product_code":"DG813","sales_period":false,"deal":false,"deal_code":"NA","customer_code":"NW761","online":true},{"id":11435,"date":1661655792000,"product_code":"BD603","sales_period":true,"deal":false,"deal_code":"NA","customer_code":"AB220","online":true},{"id":11436,"date":1653187079000,"product_code":"SP405","sales_period":false,"deal":false,"deal_code":"NA","customer_code":"CM971","online":true},{"id":11437,"date":1610228298000,"product_code":"HI384","sales_period":false,"deal":false,"deal_code":"NA","customer_code":"AS671","online":true},{"id":11438,"date":1671468386000,"product_code":"WM660","sales_period":false,"deal":false,"deal_code":"NA","customer_code":"JH499","online":true},{"id":11439,"date":1670710027000,"product_code":"AL495","sales_period":false,"deal":false,"deal_code":"NA","customer_code":"LM256","online":true},{"id":11440,"date":1620338698000,"product_code":"DG813","sales_period":false,"deal":true,"deal_code":"AP109","customer_code":"MN654","online":true},{"id":11441,"date":1635158678000,"product_code":"DG813","sales_period":false,"deal":true,"deal_code":"BL401","customer_code":"ML737","online":true},{"id":11442,"date":1686280614000,"product_code":"DM420","sales_period":true,"deal":false,"deal_code":"NA","customer_code":"CA834","online":true},{"id":11443,"date":1655323034000,"product_code":"DL822","sales_period":false,"deal":false,"deal_code":"NA","customer_code":"RO450","online":true},{"id":11444,"date":1630156503000,"product_code":"HI384","sales_period":false,"deal":false,"deal_code":"NA","customer_code":"BV559","online":false},{"id":11445,"date":1641555059000,"product_code":"PD765","sales_period":true,"deal":true,"deal_code":"SB477","customer_code":"JL782","online":false},{"id":11446,"date":1665817748000,"product_code":"ML688","sales_period":false,"deal":true,"deal_code":"DM225","customer_code":"EM643","online":true},{"id":11447,"date":1641016898000,"product_code":"DP527","sales_period":true,"deal":false,"deal_code":"NA","customer_code":"DT533","online":true},{"id":11448,"date":1665855017000,"product_code":"PD765","sales_period":false,"deal":false,"deal_code":"NA","customer_code":"KW989","online":true},{"id":11449,"date":1637206851000,"product_code":"SL845","sales_period":false,"deal":false,"deal_code":"NA","customer_code":"AW842","online":true},{"id":11450,"date":1641272905000,"product_code":"ML688","sales_period":true,"deal":true,"deal_code":"LS105","customer_code":"RB592","online":true},{"id":11451,"date":1624006347000,"product_code":"DK984","sales_period":true,"deal":false,"deal_code":"NA","customer_code":"CG133","online":true},{"id":11452,"date":1611889255000,"product_code":"DM420","sales_period":true,"deal":false,"deal_code":"NA","customer_code":"DB598","online":true},{"id":11453,"date":1659352334000,"product_code":"PD765","sales_period":false,"deal":false,"deal_code":"NA","customer_code":"MR278","online":true},{"id":11454,"date":1613052956000,"product_code":"PS755","sales_period":false,"deal":true,"deal_code":"LS105","customer_code":"AF774","online":false},{"id":11455,"date":1658401823000,"product_code":"DK984","sales_period":false,"deal":false,"deal_code":"NA","customer_code":"DL376","online":false},{"id":11456,"date":1618723644000,"product_code":"DM420","sales_period":false,"deal":false,"deal_code":"NA","customer_code":"CF537","online":true},{"id":11457,"date":1667945374000,"product_code":"SP405","sales_period":false,"deal":false,"deal_code":"NA","customer_code":"JW601","online":true},{"id":11458,"date":1649113143000,"product_code":"SL845","sales_period":false,"deal":true,"deal_code":"LS105","customer_code":"AM346","online":true},{"id":11459,"date":1618031370000,"product_code":"GD124","sales_period":false,"deal":true,"deal_code":"AP109","customer_code":"LH916","online":true},{"id":11460,"date":1649426333000,"product_code":"DL822","sales_period":false,"deal":false,"deal_code":"NA","customer_code":"VW350","online":true},{"id":11461,"date":1615611775000,"product_code":"DG813","sales_period":false,"deal":false,"deal_code":"NA","customer_code":"LB227","online":true},{"id":11462,"date":1611019033000,"product_code":"RM246","sales_period":true,"deal":false,"deal_code":"NA","customer_code":"RW213","online":true},{"id":11463,"date":1648559062000,"product_code":"MD365","sales_period":false,"deal":false,"deal_code":"NA","customer_code":"RR115","online":true},{"id":11464,"date":1672863372000,"product_code":"DK984","sales_period":true,"deal":false,"deal_code":"NA","customer_code":"SK542","online":true},{"id":11465,"date":1678104173000,"product_code":"DM420","sales_period":false,"deal":true,"deal_code":"SB477","customer_code":"MF509","online":true},{"id":11466,"date":1678328621000,"product_code":"RS630","sales_period":false,"deal":false,"deal_code":"NA","customer_code":"CJ586","online":true},{"id":11467,"date":1617980618000,"product_code":"AL495","sales_period":false,"deal":false,"deal_code":"NA","customer_code":"DW919","online":true},{"id":11468,"date":1630405657000,"product_code":"PD765","sales_period":false,"deal":false,"deal_code":"NA","customer_code":"RM238","online":false},{"id":11469,"date":1651844339000,"product_code":"DK984","sales_period":false,"deal":false,"deal_code":"NA","customer_code":"CS430","online":false},{"id":11470,"date":1620918100000,"product_code":"MD365","sales_period":false,"deal":false,"deal_code":"NA","customer_code":"TT378","online":false},{"id":11471,"date":1620580213000,"product_code":"BD603","sales_period":false,"deal":true,"deal_code":"BL401","customer_code":"CH627","online":true},{"id":11472,"date":1687518656000,"product_code":"ML688","sales_period":true,"deal":true,"deal_code":"DM225","customer_code":"AH964","online":true},{"id":11473,"date":1625146724000,"product_code":"DL822","sales_period":true,"deal":false,"deal_code":"NA","customer_code":"CE195","online":true},{"id":11474,"date":1689319117000,"product_code":"HI384","sales_period":false,"deal":false,"deal_code":"NA","customer_code":"EK447","online":true},{"id":11475,"date":1673602263000,"product_code":"DP527","sales_period":true,"deal":false,"deal_code":"NA","customer_code":"RM596","online":true},{"id":11476,"date":1646510300000,"product_code":"SP405","sales_period":false,"deal":false,"deal_code":"NA","customer_code":"PB552","online":true},{"id":11477,"date":1657636489000,"product_code":"PS755","sales_period":false,"deal":false,"deal_code":"NA","customer_code":"NC530","online":true},{"id":11478,"date":1624660136000,"product_code":"AL495","sales_period":false,"deal":true,"deal_code":"LS105","customer_code":"AM383","online":true},{"id":11479,"date":1661070715000,"product_code":"BD603","sales_period":true,"deal":false,"deal_code":"NA","customer_code":"MH321","online":true},{"id":11480,"date":1618987651000,"product_code":"MD365","sales_period":false,"deal":false,"deal_code":"NA","customer_code":"SL141","online":true},{"id":11481,"date":1672663791000,"product_code":"RM246","sales_period":false,"deal":true,"deal_code":"LS105","customer_code":"WO856","online":true},{"id":11482,"date":1620351930000,"product_code":"DM420","sales_period":false,"deal":true,"deal_code":"DM225","customer_code":"TB982","online":true},{"id":11483,"date":1616188859000,"product_code":"DK984","sales_period":false,"deal":true,"deal_code":"AP109","customer_code":"AD347","online":true},{"id":11484,"date":1687074261000,"product_code":"NH575","sales_period":true,"deal":false,"deal_code":"NA","customer_code":"ML896","online":true},{"id":11485,"date":1652884323000,"product_code":"NH575","sales_period":false,"deal":false,"deal_code":"NA","customer_code":"JP747","online":true},{"id":11486,"date":1633386652000,"product_code":"WM660","sales_period":false,"deal":false,"deal_code":"NA","customer_code":"SY843","online":true},{"id":11487,"date":1673238464000,"product_code":"NH575","sales_period":true,"deal":false,"deal_code":"NA","customer_code":"VB558","online":true},{"id":11488,"date":1668526680000,"product_code":"DK984","sales_period":false,"deal":false,"deal_code":"NA","customer_code":"CS291","online":true},{"id":11489,"date":1616605906000,"product_code":"DL822","sales_period":false,"deal":false,"deal_code":"NA","customer_code":"AB155","online":false},{"id":11490,"date":1669811329000,"product_code":"MD365","sales_period":false,"deal":false,"deal_code":"NA","customer_code":"JL863","online":true},{"id":11491,"date":1679755249000,"product_code":"RS630","sales_period":false,"deal":false,"deal_code":"NA","customer_code":"JR854","online":true},{"id":11492,"date":1623782665000,"product_code":"RS630","sales_period":false,"deal":true,"deal_code":"BL401","customer_code":"CH516","online":true},{"id":11493,"date":1630808308000,"product_code":"DM420","sales_period":false,"deal":false,"deal_code":"NA","customer_code":"AM687","online":true},{"id":11494,"date":1643532276000,"product_code":"GD124","sales_period":false,"deal":false,"deal_code":"NA","customer_code":"AJ485","online":true},{"id":11495,"date":1620159179000,"product_code":"SL845","sales_period":false,"deal":true,"deal_code":"AP109","customer_code":"TN539","online":true},{"id":11496,"date":1678774520000,"product_code":"GD124","sales_period":false,"deal":true,"deal_code":"DM225","customer_code":"JR290","online":true},{"id":11497,"date":1652529711000,"product_code":"DK984","sales_period":false,"deal":false,"deal_code":"NA","customer_code":"RD266","online":true},{"id":11498,"date":1645818298000,"product_code":"ML688","sales_period":false,"deal":false,"deal_code":"NA","customer_code":"TS470","online":true},{"id":11499,"date":1660933596000,"product_code":"RS630","sales_period":true,"deal":true,"deal_code":"AP109","customer_code":"BC852","online":true},{"id":11500,"date":1610978556000,"product_code":"DK984","sales_period":false,"deal":false,"deal_code":"NA","customer_code":"JB504","online":true},{"id":11501,"date":1687837768000,"product_code":"HI384","sales_period":true,"deal":false,"deal_code":"NA","customer_code":"JD990","online":true},{"id":11502,"date":1609924866000,"product_code":"DP527","sales_period":true,"deal":false,"deal_code":"NA","customer_code":"MH521","online":true},{"id":11503,"date":1687193309000,"product_code":"BD603","sales_period":true,"deal":true,"deal_code":"SB477","customer_code":"MW598","online":true},{"id":11504,"date":1623724561000,"product_code":"ML688","sales_period":true,"deal":true,"deal_code":"AP109","customer_code":"CC193","online":true},{"id":11505,"date":1610983330000,"product_code":"DM420","sales_period":true,"deal":false,"deal_code":"NA","customer_code":"MM369","online":true},{"id":11506,"date":1659758623000,"product_code":"DM420","sales_period":true,"deal":false,"deal_code":"NA","customer_code":"RC110","online":true},{"id":11507,"date":1621844728000,"product_code":"DG813","sales_period":false,"deal":true,"deal_code":"DM225","customer_code":"RB606","online":true},{"id":11508,"date":1686575286000,"product_code":"PS755","sales_period":true,"deal":false,"deal_code":"NA","customer_code":"BH295","online":true},{"id":11509,"date":1665640973000,"product_code":"RS630","sales_period":false,"deal":false,"deal_code":"NA","customer_code":"DS532","online":true},{"id":11510,"date":1626145232000,"product_code":"PS755","sales_period":false,"deal":false,"deal_code":"NA","customer_code":"WG847","online":true},{"id":11511,"date":1662675331000,"product_code":"WM660","sales_period":false,"deal":false,"deal_code":"NA","customer_code":"SA156","online":true},{"id":11512,"date":1649183897000,"product_code":"SL845","sales_period":false,"deal":false,"deal_code":"NA","customer_code":"CC203","online":true},{"id":11513,"date":1642862730000,"product_code":"MD365","sales_period":true,"deal":true,"deal_code":"LS105","customer_code":"IO894","online":true},{"id":11514,"date":1627023527000,"product_code":"DL822","sales_period":true,"deal":false,"deal_code":"NA","customer_code":"TH945","online":true},{"id":11515,"date":1677103278000,"product_code":"NH575","sales_period":false,"deal":false,"deal_code":"NA","customer_code":"JV816","online":true},{"id":11516,"date":1649582173000,"product_code":"ML688","sales_period":false,"deal":true,"deal_code":"SB477","customer_code":"GC225","online":true},{"id":11517,"date":1625975887000,"product_code":"DK984","sales_period":false,"deal":true,"deal_code":"LS105","customer_code":"BL919","online":true},{"id":11518,"date":1655441332000,"product_code":"NH575","sales_period":false,"deal":false,"deal_code":"NA","customer_code":"SM701","online":true},{"id":11519,"date":1621512533000,"product_code":"RM246","sales_period":false,"deal":false,"deal_code":"NA","customer_code":"FC180","online":true},{"id":11520,"date":1611436793000,"product_code":"BD603","sales_period":true,"deal":false,"deal_code":"NA","customer_code":"GG355","online":true},{"id":11521,"date":1682166165000,"product_code":"DD980","sales_period":false,"deal":false,"deal_code":"NA","customer_code":"JP131","online":true},{"id":11522,"date":1670155529000,"product_code":"PS755","sales_period":false,"deal":true,"deal_code":"DM225","customer_code":"JM803","online":true},{"id":11523,"date":1660487823000,"product_code":"DM420","sales_period":false,"deal":true,"deal_code":"SB477","customer_code":"EW450","online":true},{"id":11524,"date":1612410037000,"product_code":"GD124","sales_period":false,"deal":false,"deal_code":"NA","customer_code":"JK748","online":true},{"id":11525,"date":1641780807000,"product_code":"ML688","sales_period":true,"deal":true,"deal_code":"BL401","customer_code":"SW377","online":true},{"id":11526,"date":1673972757000,"product_code":"NH575","sales_period":true,"deal":false,"deal_code":"NA","customer_code":"SM157","online":false},{"id":11527,"date":1635202573000,"product_code":"RS630","sales_period":false,"deal":true,"deal_code":"BL401","customer_code":"HT719","online":true},{"id":11528,"date":1686655402000,"product_code":"ML688","sales_period":false,"deal":true,"deal_code":"BL401","customer_code":"AB416","online":true},{"id":11529,"date":1671527717000,"product_code":"WM660","sales_period":false,"deal":false,"deal_code":"NA","customer_code":"BB860","online":false},{"id":11530,"date":1661775859000,"product_code":"DP527","sales_period":true,"deal":false,"deal_code":"NA","customer_code":"LJ257","online":false},{"id":11531,"date":1681211567000,"product_code":"DM420","sales_period":false,"deal":false,"deal_code":"NA","customer_code":"AF196","online":false},{"id":11532,"date":1674621568000,"product_code":"RM246","sales_period":false,"deal":true,"deal_code":"AP109","customer_code":"BM706","online":true},{"id":11533,"date":1619876401000,"product_code":"PD765","sales_period":false,"deal":false,"deal_code":"NA","customer_code":"AV639","online":false},{"id":11534,"date":1660235791000,"product_code":"SP405","sales_period":true,"deal":false,"deal_code":"NA","customer_code":"AR856","online":true},{"id":11535,"date":1631739334000,"product_code":"DM420","sales_period":false,"deal":true,"deal_code":"LS105","customer_code":"CP967","online":true},{"id":11536,"date":1610823861000,"product_code":"ML688","sales_period":false,"deal":false,"deal_code":"NA","customer_code":"MP788","online":true},{"id":11537,"date":1620370191000,"product_code":"RM246","sales_period":false,"deal":true,"deal_code":"AP109","customer_code":"LR825","online":true},{"id":11538,"date":1641085340000,"product_code":"RM246","sales_period":true,"deal":false,"deal_code":"NA","customer_code":"BF993","online":true},{"id":11539,"date":1672947853000,"product_code":"DD980","sales_period":false,"deal":false,"deal_code":"NA","customer_code":"AL644","online":true},{"id":11540,"date":1644968719000,"product_code":"ML688","sales_period":false,"deal":false,"deal_code":"NA","customer_code":"TM850","online":true},{"id":11541,"date":1624379284000,"product_code":"PD765","sales_period":true,"deal":false,"deal_code":"NA","customer_code":"EJ935","online":true},{"id":11542,"date":1659796920000,"product_code":"RS630","sales_period":true,"deal":false,"deal_code":"NA","customer_code":"BP143","online":true},{"id":11543,"date":1640357038000,"product_code":"HI384","sales_period":false,"deal":false,"deal_code":"NA","customer_code":"MJ297","online":true},{"id":11544,"date":1638860533000,"product_code":"NH575","sales_period":false,"deal":true,"deal_code":"DM225","customer_code":"SB459","online":true},{"id":11545,"date":1687473732000,"product_code":"MD365","sales_period":true,"deal":false,"deal_code":"NA","customer_code":"KH117","online":true},{"id":11546,"date":1619681961000,"product_code":"NH575","sales_period":false,"deal":false,"deal_code":"NA","customer_code":"LB548","online":true},{"id":11547,"date":1673692857000,"product_code":"DM420","sales_period":false,"deal":false,"deal_code":"NA","customer_code":"CL525","online":true},{"id":11548,"date":1674479961000,"product_code":"DM420","sales_period":true,"deal":true,"deal_code":"BL401","customer_code":"TS202","online":true},{"id":11549,"date":1688157868000,"product_code":"SL845","sales_period":true,"deal":false,"deal_code":"NA","customer_code":"AM968","online":true},{"id":11550,"date":1613094682000,"product_code":"ML688","sales_period":false,"deal":true,"deal_code":"SB477","customer_code":"RL294","online":true},{"id":11551,"date":1685910384000,"product_code":"NH575","sales_period":false,"deal":true,"deal_code":"AP109","customer_code":"CL455","online":true},{"id":11552,"date":1637891411000,"product_code":"RM246","sales_period":false,"deal":true,"deal_code":"BL401","customer_code":"SM488","online":true},{"id":11553,"date":1674455262000,"product_code":"DP527","sales_period":false,"deal":true,"deal_code":"AP109","customer_code":"MD625","online":true},{"id":11554,"date":1649778514000,"product_code":"RS630","sales_period":false,"deal":false,"deal_code":"NA","customer_code":"AM715","online":true},{"id":11555,"date":1645548584000,"product_code":"DP527","sales_period":false,"deal":false,"deal_code":"NA","customer_code":"JH746","online":true},{"id":11556,"date":1636152535000,"product_code":"DL822","sales_period":false,"deal":false,"deal_code":"NA","customer_code":"SJ546","online":true},{"id":11557,"date":1641626316000,"product_code":"BD603","sales_period":true,"deal":true,"deal_code":"DM225","customer_code":"ND291","online":true},{"id":11558,"date":1683119355000,"product_code":"HI384","sales_period":false,"deal":true,"deal_code":"DM225","customer_code":"GM116","online":true},{"id":11559,"date":1664516015000,"product_code":"MD365","sales_period":false,"deal":false,"deal_code":"NA","customer_code":"DW790","online":true},{"id":11560,"date":1686105342000,"product_code":"MD365","sales_period":true,"deal":false,"deal_code":"NA","customer_code":"RC167","online":true},{"id":11561,"date":1639985011000,"product_code":"DK984","sales_period":false,"deal":true,"deal_code":"AP109","customer_code":"AS402","online":true},{"id":11562,"date":1614081681000,"product_code":"WM660","sales_period":false,"deal":false,"deal_code":"NA","customer_code":"MV730","online":true},{"id":11563,"date":1681494859000,"product_code":"DL822","sales_period":false,"deal":false,"deal_code":"NA","customer_code":"CD290","online":true},{"id":11564,"date":1660891592000,"product_code":"MD365","sales_period":false,"deal":false,"deal_code":"NA","customer_code":"TG894","online":true},{"id":11565,"date":1667857428000,"product_code":"RM246","sales_period":false,"deal":false,"deal_code":"NA","customer_code":"AS271","online":true},{"id":11566,"date":1639861071000,"product_code":"NH575","sales_period":false,"deal":false,"deal_code":"NA","customer_code":"ES480","online":true},{"id":11567,"date":1609914786000,"product_code":"DL822","sales_period":true,"deal":true,"deal_code":"BL401","customer_code":"SS790","online":true},{"id":11568,"date":1659737122000,"product_code":"PS755","sales_period":true,"deal":false,"deal_code":"NA","customer_code":"BR453","online":true},{"id":11569,"date":1688347985000,"product_code":"ML688","sales_period":false,"deal":true,"deal_code":"SB477","customer_code":"AH469","online":true},{"id":11570,"date":1609481067000,"product_code":"BD603","sales_period":true,"deal":false,"deal_code":"NA","customer_code":"KW820","online":true},{"id":11571,"date":1611038883000,"product_code":"AL495","sales_period":true,"deal":false,"deal_code":"NA","customer_code":"EJ408","online":true},{"id":11572,"date":1610491631000,"product_code":"RS630","sales_period":true,"deal":false,"deal_code":"NA","customer_code":"JG698","online":true},{"id":11573,"date":1627687759000,"product_code":"DP527","sales_period":false,"deal":true,"deal_code":"DM225","customer_code":"KP635","online":true},{"id":11574,"date":1675564022000,"product_code":"DP527","sales_period":false,"deal":true,"deal_code":"SB477","customer_code":"JA441","online":true},{"id":11575,"date":1673294289000,"product_code":"RM246","sales_period":false,"deal":false,"deal_code":"NA","customer_code":"CD988","online":true},{"id":11576,"date":1690085467000,"product_code":"WM660","sales_period":false,"deal":false,"deal_code":"NA","customer_code":"SC474","online":true},{"id":11577,"date":1664349331000,"product_code":"DM420","sales_period":false,"deal":false,"deal_code":"NA","customer_code":"RH238","online":true},{"id":11578,"date":1685960355000,"product_code":"DD980","sales_period":false,"deal":true,"deal_code":"SB477","customer_code":"SH661","online":true},{"id":11579,"date":1690180344000,"product_code":"RM246","sales_period":false,"deal":false,"deal_code":"NA","customer_code":"PH736","online":true},{"id":11580,"date":1609593305000,"product_code":"SL845","sales_period":false,"deal":false,"deal_code":"NA","customer_code":"VD536","online":false},{"id":11581,"date":1658141696000,"product_code":"DD980","sales_period":false,"deal":false,"deal_code":"NA","customer_code":"AG960","online":true},{"id":11582,"date":1661925451000,"product_code":"DP527","sales_period":false,"deal":false,"deal_code":"NA","customer_code":"JM234","online":true},{"id":11583,"date":1668196811000,"product_code":"GD124","sales_period":false,"deal":false,"deal_code":"NA","customer_code":"JW247","online":true},{"id":11584,"date":1677456414000,"product_code":"NH575","sales_period":false,"deal":false,"deal_code":"NA","customer_code":"MS317","online":true},{"id":11585,"date":1672137240000,"product_code":"DM420","sales_period":false,"deal":true,"deal_code":"SB477","customer_code":"JM530","online":true},{"id":11586,"date":1649162842000,"product_code":"DD980","sales_period":false,"deal":false,"deal_code":"NA","customer_code":"SO250","online":true},{"id":11587,"date":1640156210000,"product_code":"RS630","sales_period":false,"deal":true,"deal_code":"BL401","customer_code":"DY886","online":true},{"id":11588,"date":1659342575000,"product_code":"DG813","sales_period":true,"deal":false,"deal_code":"NA","customer_code":"RD431","online":true},{"id":11589,"date":1633782526000,"product_code":"SP405","sales_period":false,"deal":true,"deal_code":"AP109","customer_code":"DB858","online":true},{"id":11590,"date":1655438372000,"product_code":"SP405","sales_period":false,"deal":true,"deal_code":"SB477","customer_code":"RN115","online":true},{"id":11591,"date":1683863016000,"product_code":"BD603","sales_period":false,"deal":true,"deal_code":"SB477","customer_code":"JG431","online":true},{"id":11592,"date":1657990919000,"product_code":"RS630","sales_period":false,"deal":false,"deal_code":"NA","customer_code":"WA421","online":true},{"id":11593,"date":1643043017000,"product_code":"HI384","sales_period":true,"deal":false,"deal_code":"NA","customer_code":"PW183","online":true},{"id":11594,"date":1684631553000,"product_code":"MD365","sales_period":false,"deal":true,"deal_code":"AP109","customer_code":"MH927","online":true},{"id":11595,"date":1610483136000,"product_code":"DD980","sales_period":true,"deal":true,"deal_code":"DM225","customer_code":"SB690","online":true},{"id":11596,"date":1639422564000,"product_code":"RM246","sales_period":false,"deal":false,"deal_code":"NA","customer_code":"MB199","online":true},{"id":11597,"date":1667483847000,"product_code":"DM420","sales_period":false,"deal":false,"deal_code":"NA","customer_code":"SH668","online":true},{"id":11598,"date":1679955963000,"product_code":"DP527","sales_period":false,"deal":true,"deal_code":"SB477","customer_code":"TB328","online":true},{"id":11599,"date":1663045384000,"product_code":"DK984","sales_period":false,"deal":true,"deal_code":"AP109","customer_code":"JK704","online":true},{"id":11600,"date":1664198399000,"product_code":"AL495","sales_period":false,"deal":false,"deal_code":"NA","customer_code":"FW558","online":true},{"id":11601,"date":1687359161000,"product_code":"AL495","sales_period":false,"deal":false,"deal_code":"NA","customer_code":"LC287","online":true},{"id":11602,"date":1667953879000,"product_code":"DM420","sales_period":false,"deal":false,"deal_code":"NA","customer_code":"DV372","online":true},{"id":11603,"date":1609700724000,"product_code":"HI384","sales_period":true,"deal":false,"deal_code":"NA","customer_code":"JH557","online":true},{"id":11604,"date":1692544218000,"product_code":"DK984","sales_period":false,"deal":false,"deal_code":"NA","customer_code":"EB210","online":true},{"id":11605,"date":1683749686000,"product_code":"SL845","sales_period":false,"deal":false,"deal_code":"NA","customer_code":"TH672","online":true},{"id":11606,"date":1659520395000,"product_code":"SP405","sales_period":true,"deal":false,"deal_code":"NA","customer_code":"FW322","online":true},{"id":11607,"date":1609477331000,"product_code":"MD365","sales_period":true,"deal":false,"deal_code":"NA","customer_code":"TR451","online":true},{"id":11608,"date":1660815505000,"product_code":"SL845","sales_period":true,"deal":true,"deal_code":"DM225","customer_code":"IT465","online":true},{"id":11609,"date":1640289297000,"product_code":"ML688","sales_period":false,"deal":true,"deal_code":"DM225","customer_code":"AJ370","online":true},{"id":11610,"date":1610672255000,"product_code":"DD980","sales_period":false,"deal":false,"deal_code":"NA","customer_code":"MM133","online":true},{"id":11611,"date":1685649106000,"product_code":"PS755","sales_period":false,"deal":false,"deal_code":"NA","customer_code":"PR730","online":true},{"id":11612,"date":1685637321000,"product_code":"PS755","sales_period":true,"deal":false,"deal_code":"NA","customer_code":"CW468","online":true},{"id":11613,"date":1664357437000,"product_code":"PS755","sales_period":false,"deal":true,"deal_code":"AP109","customer_code":"LO472","online":true},{"id":11614,"date":1619892531000,"product_code":"DP527","sales_period":false,"deal":true,"deal_code":"BL401","customer_code":"BR427","online":true},{"id":11615,"date":1646610751000,"product_code":"DM420","sales_period":false,"deal":false,"deal_code":"NA","customer_code":"KE470","online":true},{"id":11616,"date":1673127909000,"product_code":"AL495","sales_period":true,"deal":false,"deal_code":"NA","customer_code":"MR406","online":true},{"id":11617,"date":1638015505000,"product_code":"GD124","sales_period":false,"deal":false,"deal_code":"NA","customer_code":"RB626","online":true},{"id":11618,"date":1615950119000,"product_code":"GD124","sales_period":false,"deal":false,"deal_code":"NA","customer_code":"NW827","online":true},{"id":11619,"date":1625882735000,"product_code":"AL495","sales_period":false,"deal":true,"deal_code":"SB477","customer_code":"TT116","online":true},{"id":11620,"date":1674184579000,"product_code":"DM420","sales_period":true,"deal":true,"deal_code":"BL401","customer_code":"RB996","online":true},{"id":11621,"date":1614530288000,"product_code":"PD765","sales_period":false,"deal":false,"deal_code":"NA","customer_code":"CG583","online":true},{"id":11622,"date":1673004033000,"product_code":"ML688","sales_period":true,"deal":false,"deal_code":"NA","customer_code":"AR328","online":false},{"id":11623,"date":1670675780000,"product_code":"SL845","sales_period":false,"deal":true,"deal_code":"AP109","customer_code":"DW642","online":true},{"id":11624,"date":1652268479000,"product_code":"GD124","sales_period":false,"deal":false,"deal_code":"NA","customer_code":"SS184","online":true},{"id":11625,"date":1680989089000,"product_code":"DG813","sales_period":false,"deal":false,"deal_code":"NA","customer_code":"MF896","online":true},{"id":11626,"date":1660776251000,"product_code":"BD603","sales_period":true,"deal":false,"deal_code":"NA","customer_code":"WJ613","online":true},{"id":11627,"date":1610702108000,"product_code":"HI384","sales_period":true,"deal":false,"deal_code":"NA","customer_code":"JW560","online":true},{"id":11628,"date":1673673560000,"product_code":"NH575","sales_period":true,"deal":false,"deal_code":"NA","customer_code":"SC704","online":true},{"id":11629,"date":1669153692000,"product_code":"DM420","sales_period":false,"deal":true,"deal_code":"AP109","customer_code":"DC105","online":true},{"id":11630,"date":1646591243000,"product_code":"DD980","sales_period":false,"deal":false,"deal_code":"NA","customer_code":"AM871","online":false},{"id":11631,"date":1645877035000,"product_code":"SP405","sales_period":false,"deal":false,"deal_code":"NA","customer_code":"LF426","online":true},{"id":11632,"date":1686219703000,"product_code":"SP405","sales_period":true,"deal":false,"deal_code":"NA","customer_code":"HM671","online":true},{"id":11633,"date":1692490855000,"product_code":"DL822","sales_period":false,"deal":false,"deal_code":"NA","customer_code":"TM144","online":true},{"id":11634,"date":1673672415000,"product_code":"SL845","sales_period":true,"deal":false,"deal_code":"NA","customer_code":"BH935","online":true},{"id":11635,"date":1673799754000,"product_code":"RS630","sales_period":true,"deal":false,"deal_code":"NA","customer_code":"JB182","online":true},{"id":11636,"date":1664604530000,"product_code":"NH575","sales_period":false,"deal":true,"deal_code":"BL401","customer_code":"AS609","online":true},{"id":11637,"date":1673175143000,"product_code":"HI384","sales_period":false,"deal":true,"deal_code":"LS105","customer_code":"SW730","online":true},{"id":11638,"date":1672841873000,"product_code":"GD124","sales_period":true,"deal":false,"deal_code":"NA","customer_code":"KW962","online":true},{"id":11639,"date":1610226699000,"product_code":"ML688","sales_period":false,"deal":false,"deal_code":"NA","customer_code":"MH964","online":true},{"id":11640,"date":1661690631000,"product_code":"DP527","sales_period":true,"deal":false,"deal_code":"NA","customer_code":"JC892","online":true},{"id":11641,"date":1623650602000,"product_code":"RM246","sales_period":true,"deal":false,"deal_code":"NA","customer_code":"CD605","online":true},{"id":11642,"date":1673177016000,"product_code":"DP527","sales_period":true,"deal":false,"deal_code":"NA","customer_code":"SD835","online":true},{"id":11643,"date":1678413856000,"product_code":"NH575","sales_period":false,"deal":false,"deal_code":"NA","customer_code":"JD253","online":true},{"id":11644,"date":1632243957000,"product_code":"BD603","sales_period":false,"deal":false,"deal_code":"NA","customer_code":"SG291","online":true},{"id":11645,"date":1661239721000,"product_code":"SL845","sales_period":true,"deal":false,"deal_code":"NA","customer_code":"KS693","online":true},{"id":11646,"date":1663209046000,"product_code":"HI384","sales_period":false,"deal":true,"deal_code":"AP109","customer_code":"SP685","online":true},{"id":11647,"date":1661479419000,"product_code":"RM246","sales_period":false,"deal":false,"deal_code":"NA","customer_code":"SA670","online":true},{"id":11648,"date":1652848984000,"product_code":"PD765","sales_period":false,"deal":true,"deal_code":"DM225","customer_code":"RS128","online":true},{"id":11649,"date":1626236633000,"product_code":"ML688","sales_period":false,"deal":false,"deal_code":"NA","customer_code":"JW878","online":true},{"id":11650,"date":1626342986000,"product_code":"DP527","sales_period":false,"deal":false,"deal_code":"NA","customer_code":"JJ109","online":true},{"id":11651,"date":1683780126000,"product_code":"RM246","sales_period":false,"deal":false,"deal_code":"NA","customer_code":"RW627","online":true},{"id":11652,"date":1634118424000,"product_code":"PD765","sales_period":false,"deal":false,"deal_code":"NA","customer_code":"MM124","online":true},{"id":11653,"date":1686839392000,"product_code":"RM246","sales_period":true,"deal":false,"deal_code":"NA","customer_code":"FG430","online":false},{"id":11654,"date":1659415247000,"product_code":"HI384","sales_period":false,"deal":true,"deal_code":"SB477","customer_code":"DK873","online":true},{"id":11655,"date":1666766232000,"product_code":"AL495","sales_period":false,"deal":true,"deal_code":"AP109","customer_code":"NH755","online":true},{"id":11656,"date":1617743857000,"product_code":"NH575","sales_period":false,"deal":true,"deal_code":"LS105","customer_code":"DL728","online":true},{"id":11657,"date":1623822494000,"product_code":"NH575","sales_period":true,"deal":false,"deal_code":"NA","customer_code":"JK891","online":true},{"id":11658,"date":1622898748000,"product_code":"MD365","sales_period":true,"deal":true,"deal_code":"AP109","customer_code":"CH603","online":true},{"id":11659,"date":1641027523000,"product_code":"BD603","sales_period":true,"deal":false,"deal_code":"NA","customer_code":"MT704","online":true},{"id":11660,"date":1674942917000,"product_code":"NH575","sales_period":true,"deal":true,"deal_code":"LS105","customer_code":"MJ700","online":true},{"id":11661,"date":1639270467000,"product_code":"SL845","sales_period":false,"deal":false,"deal_code":"NA","customer_code":"HH282","online":true},{"id":11662,"date":1668923141000,"product_code":"DK984","sales_period":false,"deal":true,"deal_code":"DM225","customer_code":"RM672","online":true},{"id":11663,"date":1661253390000,"product_code":"DK984","sales_period":false,"deal":true,"deal_code":"DM225","customer_code":"BM119","online":true},{"id":11664,"date":1682745135000,"product_code":"BD603","sales_period":false,"deal":true,"deal_code":"BL401","customer_code":"SW971","online":true},{"id":11665,"date":1627464158000,"product_code":"GD124","sales_period":true,"deal":false,"deal_code":"NA","customer_code":"RM743","online":true},{"id":11666,"date":1684863501000,"product_code":"GD124","sales_period":false,"deal":false,"deal_code":"NA","customer_code":"JL909","online":true},{"id":11667,"date":1659202982000,"product_code":"MD365","sales_period":false,"deal":true,"deal_code":"AP109","customer_code":"JH469","online":false},{"id":11668,"date":1658564371000,"product_code":"PD765","sales_period":false,"deal":false,"deal_code":"NA","customer_code":"JL220","online":true},{"id":11669,"date":1667415695000,"product_code":"MD365","sales_period":false,"deal":false,"deal_code":"NA","customer_code":"AC176","online":true},{"id":11670,"date":1682007363000,"product_code":"AL495","sales_period":false,"deal":false,"deal_code":"NA","customer_code":"AC681","online":true},{"id":11671,"date":1659403739000,"product_code":"SL845","sales_period":true,"deal":false,"deal_code":"NA","customer_code":"BB679","online":true},{"id":11672,"date":1672822566000,"product_code":"DL822","sales_period":true,"deal":false,"deal_code":"NA","customer_code":"SK674","online":true},{"id":11673,"date":1616814360000,"product_code":"PS755","sales_period":false,"deal":false,"deal_code":"NA","customer_code":"SJ796","online":true},{"id":11674,"date":1680096940000,"product_code":"ML688","sales_period":false,"deal":false,"deal_code":"NA","customer_code":"BG862","online":true},{"id":11675,"date":1609892006000,"product_code":"SL845","sales_period":true,"deal":false,"deal_code":"NA","customer_code":"JY532","online":true},{"id":11676,"date":1685751726000,"product_code":"RS630","sales_period":true,"deal":false,"deal_code":"NA","customer_code":"JG699","online":true},{"id":11677,"date":1663040708000,"product_code":"DP527","sales_period":false,"deal":false,"deal_code":"NA","customer_code":"KJ292","online":true},{"id":11678,"date":1636563451000,"product_code":"DP527","sales_period":false,"deal":false,"deal_code":"NA","customer_code":"SR671","online":true},{"id":11679,"date":1688041028000,"product_code":"PS755","sales_period":true,"deal":true,"deal_code":"BL401","customer_code":"JP575","online":true},{"id":11680,"date":1662392936000,"product_code":"SP405","sales_period":false,"deal":false,"deal_code":"NA","customer_code":"MB287","online":true},{"id":11681,"date":1691654398000,"product_code":"WM660","sales_period":false,"deal":true,"deal_code":"AP109","customer_code":"MH711","online":true},{"id":11682,"date":1632717817000,"product_code":"ML688","sales_period":false,"deal":false,"deal_code":"NA","customer_code":"CB203","online":true},{"id":11683,"date":1659242456000,"product_code":"SP405","sales_period":false,"deal":false,"deal_code":"NA","customer_code":"NM838","online":true},{"id":11684,"date":1654532265000,"product_code":"RM246","sales_period":false,"deal":false,"deal_code":"NA","customer_code":"SJ548","online":true},{"id":11685,"date":1629762273000,"product_code":"DG813","sales_period":false,"deal":true,"deal_code":"DM225","customer_code":"JB806","online":true},{"id":11686,"date":1674459231000,"product_code":"DG813","sales_period":false,"deal":false,"deal_code":"NA","customer_code":"JR164","online":true},{"id":11687,"date":1641798803000,"product_code":"RS630","sales_period":true,"deal":false,"deal_code":"NA","customer_code":"BG110","online":true},{"id":11688,"date":1657033333000,"product_code":"DP527","sales_period":false,"deal":false,"deal_code":"NA","customer_code":"AB774","online":false},{"id":11689,"date":1671253939000,"product_code":"DL822","sales_period":false,"deal":false,"deal_code":"NA","customer_code":"AN454","online":true},{"id":11690,"date":1622633232000,"product_code":"SL845","sales_period":true,"deal":true,"deal_code":"AP109","customer_code":"JL516","online":false},{"id":11691,"date":1657807230000,"product_code":"HI384","sales_period":false,"deal":true,"deal_code":"AP109","customer_code":"AJ856","online":true},{"id":11692,"date":1629390120000,"product_code":"PD765","sales_period":false,"deal":true,"deal_code":"LS105","customer_code":"TR260","online":false},{"id":11693,"date":1642030817000,"product_code":"BD603","sales_period":true,"deal":false,"deal_code":"NA","customer_code":"AS268","online":true},{"id":11694,"date":1681449285000,"product_code":"DL822","sales_period":false,"deal":true,"deal_code":"DM225","customer_code":"LP391","online":true},{"id":11695,"date":1649732246000,"product_code":"NH575","sales_period":false,"deal":true,"deal_code":"AP109","customer_code":"JJ657","online":true},{"id":11696,"date":1610114782000,"product_code":"DL822","sales_period":true,"deal":false,"deal_code":"NA","customer_code":"SC899","online":true},{"id":11697,"date":1635551591000,"product_code":"PD765","sales_period":false,"deal":false,"deal_code":"NA","customer_code":"CJ793","online":true},{"id":11698,"date":1680405205000,"product_code":"AL495","sales_period":false,"deal":false,"deal_code":"NA","customer_code":"DP145","online":true},{"id":11699,"date":1672942087000,"product_code":"GD124","sales_period":true,"deal":false,"deal_code":"NA","customer_code":"MB978","online":true},{"id":11700,"date":1661464192000,"product_code":"AL495","sales_period":true,"deal":false,"deal_code":"NA","customer_code":"SD166","online":true},{"id":11701,"date":1643548811000,"product_code":"DK984","sales_period":true,"deal":true,"deal_code":"AP109","customer_code":"DH122","online":true},{"id":11702,"date":1612928731000,"product_code":"DK984","sales_period":false,"deal":true,"deal_code":"SB477","customer_code":"MB269","online":true},{"id":11703,"date":1669640545000,"product_code":"MD365","sales_period":false,"deal":false,"deal_code":"NA","customer_code":"MR212","online":true},{"id":11704,"date":1623561650000,"product_code":"SP405","sales_period":true,"deal":false,"deal_code":"NA","customer_code":"AM672","online":true},{"id":11705,"date":1647610126000,"product_code":"RM246","sales_period":false,"deal":false,"deal_code":"NA","customer_code":"RR674","online":true},{"id":11706,"date":1680421410000,"product_code":"NH575","sales_period":false,"deal":false,"deal_code":"NA","customer_code":"JB791","online":true},{"id":11707,"date":1640773748000,"product_code":"WM660","sales_period":false,"deal":false,"deal_code":"NA","customer_code":"TF627","online":true},{"id":11708,"date":1672541570000,"product_code":"DM420","sales_period":true,"deal":false,"deal_code":"NA","customer_code":"JH934","online":true},{"id":11709,"date":1641178300000,"product_code":"BD603","sales_period":false,"deal":true,"deal_code":"BL401","customer_code":"KG996","online":true},{"id":11710,"date":1643804469000,"product_code":"AL495","sales_period":false,"deal":true,"deal_code":"BL401","customer_code":"SH381","online":true},{"id":11711,"date":1639621535000,"product_code":"DD980","sales_period":false,"deal":false,"deal_code":"NA","customer_code":"WM634","online":true},{"id":11712,"date":1660668101000,"product_code":"RM246","sales_period":true,"deal":false,"deal_code":"NA","customer_code":"CS504","online":true},{"id":11713,"date":1687217507000,"product_code":"DP527","sales_period":true,"deal":true,"deal_code":"AP109","customer_code":"CN493","online":true},{"id":11714,"date":1674781227000,"product_code":"RM246","sales_period":true,"deal":false,"deal_code":"NA","customer_code":"DK172","online":true},{"id":11715,"date":1678514921000,"product_code":"SP405","sales_period":false,"deal":true,"deal_code":"BL401","customer_code":"JP824","online":true},{"id":11716,"date":1641843292000,"product_code":"DP527","sales_period":true,"deal":true,"deal_code":"AP109","customer_code":"YM214","online":true},{"id":11717,"date":1616661350000,"product_code":"WM660","sales_period":false,"deal":false,"deal_code":"NA","customer_code":"BR129","online":true},{"id":11718,"date":1640114361000,"product_code":"PD765","sales_period":false,"deal":false,"deal_code":"NA","customer_code":"JM217","online":true},{"id":11719,"date":1644784030000,"product_code":"DG813","sales_period":false,"deal":false,"deal_code":"NA","customer_code":"TB248","online":true},{"id":11720,"date":1673068627000,"product_code":"DL822","sales_period":true,"deal":false,"deal_code":"NA","customer_code":"RM851","online":true},{"id":11721,"date":1684169361000,"product_code":"DP527","sales_period":false,"deal":true,"deal_code":"AP109","customer_code":"SF928","online":false},{"id":11722,"date":1625156384000,"product_code":"SL845","sales_period":false,"deal":true,"deal_code":"BL401","customer_code":"AS894","online":true},{"id":11723,"date":1610430007000,"product_code":"PS755","sales_period":false,"deal":true,"deal_code":"LS105","customer_code":"JW698","online":true},{"id":11724,"date":1611156442000,"product_code":"BD603","sales_period":true,"deal":false,"deal_code":"NA","customer_code":"BA472","online":true},{"id":11725,"date":1652317556000,"product_code":"DK984","sales_period":false,"deal":false,"deal_code":"NA","customer_code":"TM983","online":true},{"id":11726,"date":1661970327000,"product_code":"PD765","sales_period":false,"deal":true,"deal_code":"SB477","customer_code":"DV886","online":true},{"id":11727,"date":1631527666000,"product_code":"MD365","sales_period":false,"deal":true,"deal_code":"LS105","customer_code":"HB745","online":true},{"id":11728,"date":1672556640000,"product_code":"DG813","sales_period":true,"deal":true,"deal_code":"AP109","customer_code":"DN929","online":true},{"id":11729,"date":1686069102000,"product_code":"GD124","sales_period":false,"deal":false,"deal_code":"NA","customer_code":"SB778","online":true},{"id":11730,"date":1627519328000,"product_code":"DP527","sales_period":true,"deal":false,"deal_code":"NA","customer_code":"AW509","online":true},{"id":11731,"date":1611914461000,"product_code":"MD365","sales_period":true,"deal":false,"deal_code":"NA","customer_code":"AM384","online":false},{"id":11732,"date":1629654586000,"product_code":"BD603","sales_period":false,"deal":false,"deal_code":"NA","customer_code":"JT688","online":false},{"id":11733,"date":1674722036000,"product_code":"DM420","sales_period":true,"deal":true,"deal_code":"BL401","customer_code":"DK644","online":true},{"id":11734,"date":1675789672000,"product_code":"DP527","sales_period":false,"deal":false,"deal_code":"NA","customer_code":"SC729","online":true},{"id":11735,"date":1661262951000,"product_code":"ML688","sales_period":true,"deal":false,"deal_code":"NA","customer_code":"CW874","online":true},{"id":11736,"date":1614484953000,"product_code":"NH575","sales_period":false,"deal":false,"deal_code":"NA","customer_code":"DS730","online":true},{"id":11737,"date":1642193696000,"product_code":"AL495","sales_period":true,"deal":true,"deal_code":"BL401","customer_code":"JK807","online":true},{"id":11738,"date":1654618870000,"product_code":"DM420","sales_period":false,"deal":false,"deal_code":"NA","customer_code":"TA462","online":false},{"id":11739,"date":1674672731000,"product_code":"RS630","sales_period":false,"deal":false,"deal_code":"NA","customer_code":"JP336","online":true},{"id":11740,"date":1613047588000,"product_code":"DK984","sales_period":false,"deal":false,"deal_code":"NA","customer_code":"DW634","online":true},{"id":11741,"date":1610704542000,"product_code":"MD365","sales_period":true,"deal":false,"deal_code":"NA","customer_code":"JH794","online":true},{"id":11742,"date":1625228378000,"product_code":"GD124","sales_period":true,"deal":false,"deal_code":"NA","customer_code":"MH915","online":true},{"id":11743,"date":1651432161000,"product_code":"DL822","sales_period":false,"deal":false,"deal_code":"NA","customer_code":"JB895","online":true},{"id":11744,"date":1665122277000,"product_code":"SP405","sales_period":false,"deal":false,"deal_code":"NA","customer_code":"LG551","online":true},{"id":11745,"date":1688425975000,"product_code":"SP405","sales_period":false,"deal":false,"deal_code":"NA","customer_code":"JM882","online":true},{"id":11746,"date":1611727494000,"product_code":"PS755","sales_period":true,"deal":true,"deal_code":"DM225","customer_code":"KR869","online":true},{"id":11747,"date":1663745331000,"product_code":"HI384","sales_period":false,"deal":false,"deal_code":"NA","customer_code":"LO276","online":true},{"id":11748,"date":1610514900000,"product_code":"HI384","sales_period":true,"deal":true,"deal_code":"AP109","customer_code":"TA712","online":true},{"id":11749,"date":1622396597000,"product_code":"DP527","sales_period":false,"deal":true,"deal_code":"AP109","customer_code":"SC855","online":true},{"id":11750,"date":1619496573000,"product_code":"RS630","sales_period":false,"deal":true,"deal_code":"DM225","customer_code":"MC896","online":true},{"id":11751,"date":1615284576000,"product_code":"RS630","sales_period":false,"deal":true,"deal_code":"SB477","customer_code":"BM544","online":true},{"id":11752,"date":1622468959000,"product_code":"DK984","sales_period":false,"deal":false,"deal_code":"NA","customer_code":"KB642","online":true},{"id":11753,"date":1658772992000,"product_code":"RS630","sales_period":false,"deal":true,"deal_code":"DM225","customer_code":"CS438","online":true},{"id":11754,"date":1654415155000,"product_code":"MD365","sales_period":false,"deal":false,"deal_code":"NA","customer_code":"JS534","online":true},{"id":11755,"date":1686630326000,"product_code":"GD124","sales_period":true,"deal":true,"deal_code":"LS105","customer_code":"PP648","online":true},{"id":11756,"date":1687135539000,"product_code":"DP527","sales_period":true,"deal":true,"deal_code":"SB477","customer_code":"KM973","online":true},{"id":11757,"date":1645808424000,"product_code":"DD980","sales_period":false,"deal":true,"deal_code":"DM225","customer_code":"AM193","online":false},{"id":11758,"date":1684658703000,"product_code":"ML688","sales_period":false,"deal":true,"deal_code":"LS105","customer_code":"JM887","online":true},{"id":11759,"date":1624691583000,"product_code":"AL495","sales_period":true,"deal":false,"deal_code":"NA","customer_code":"MR370","online":true},{"id":11760,"date":1686200628000,"product_code":"BD603","sales_period":true,"deal":true,"deal_code":"SB477","customer_code":"JS443","online":true},{"id":11761,"date":1687980404000,"product_code":"GD124","sales_period":true,"deal":false,"deal_code":"NA","customer_code":"SD778","online":true},{"id":11762,"date":1660747479000,"product_code":"DL822","sales_period":true,"deal":false,"deal_code":"NA","customer_code":"DE300","online":true},{"id":11763,"date":1625448147000,"product_code":"SP405","sales_period":false,"deal":false,"deal_code":"NA","customer_code":"JJ205","online":true},{"id":11764,"date":1661010898000,"product_code":"GD124","sales_period":true,"deal":false,"deal_code":"NA","customer_code":"IP458","online":true},{"id":11765,"date":1647891310000,"product_code":"MD365","sales_period":false,"deal":false,"deal_code":"NA","customer_code":"ST577","online":true},{"id":11766,"date":1643344769000,"product_code":"DG813","sales_period":true,"deal":true,"deal_code":"AP109","customer_code":"JB994","online":true},{"id":11767,"date":1673429605000,"product_code":"DK984","sales_period":true,"deal":true,"deal_code":"DM225","customer_code":"AC596","online":true},{"id":11768,"date":1687979180000,"product_code":"WM660","sales_period":true,"deal":false,"deal_code":"NA","customer_code":"CH652","online":true},{"id":11769,"date":1623987299000,"product_code":"DD980","sales_period":false,"deal":false,"deal_code":"NA","customer_code":"AC411","online":true},{"id":11770,"date":1660147836000,"product_code":"DM420","sales_period":true,"deal":true,"deal_code":"LS105","customer_code":"SS341","online":false},{"id":11771,"date":1674284588000,"product_code":"SL845","sales_period":true,"deal":false,"deal_code":"NA","customer_code":"KF715","online":true},{"id":11772,"date":1662818039000,"product_code":"WM660","sales_period":false,"deal":true,"deal_code":"AP109","customer_code":"CW687","online":true},{"id":11773,"date":1624926907000,"product_code":"DP527","sales_period":true,"deal":true,"deal_code":"LS105","customer_code":"CT366","online":true},{"id":11774,"date":1643133161000,"product_code":"SL845","sales_period":true,"deal":true,"deal_code":"BL401","customer_code":"JB717","online":true},{"id":11775,"date":1673757440000,"product_code":"AL495","sales_period":true,"deal":false,"deal_code":"NA","customer_code":"KF324","online":true},{"id":11776,"date":1675704675000,"product_code":"RM246","sales_period":false,"deal":false,"deal_code":"NA","customer_code":"CC677","online":true},{"id":11777,"date":1659361240000,"product_code":"DG813","sales_period":true,"deal":false,"deal_code":"NA","customer_code":"SM589","online":true},{"id":11778,"date":1675627546000,"product_code":"SL845","sales_period":false,"deal":false,"deal_code":"NA","customer_code":"JH220","online":true},{"id":11779,"date":1669582960000,"product_code":"RM246","sales_period":false,"deal":true,"deal_code":"BL401","customer_code":"KV394","online":true},{"id":11780,"date":1609876892000,"product_code":"BD603","sales_period":true,"deal":true,"deal_code":"BL401","customer_code":"MK813","online":true}]